SIMULTAN_MeshTools/__init__.py
SIMULTAN_MeshTools/config.py
SIMULTAN_MeshTools/logger.py
SIMULTAN_MeshTools/project.py
SIMULTAN_MeshTools/template.py
SIMULTAN_MeshTools/geometry/__init__.py
SIMULTAN_MeshTools/geometry/base_geometry.py
SIMULTAN_MeshTools/geometry/extended_default_types.py
SIMULTAN_MeshTools/geometry/extended_geometry.py
SIMULTAN_MeshTools/geometry/scene.py
SIMULTAN_MeshTools/geometry/utils.py
SIMULTAN_MeshTools/gui/__init__.py
SIMULTAN_MeshTools/gui/dialogs.py
SIMULTAN_MeshTools/gui/login_frame.py
SIMULTAN_MeshTools/gui/main_window.py
SIMULTAN_MeshTools/gui/pyside6/__init__.py
SIMULTAN_MeshTools/gui/pyside6/gui.py
SIMULTAN_MeshTools/gui/pyside6/gui_utils.py
SIMULTAN_MeshTools/mesh_generation/__init__.py
SIMULTAN_MeshTools/mesh_mapper/__init__.py
SIMULTAN_MeshTools/resources/__init__.py
SIMULTAN_MeshTools/resources/mesh_template.yml
SIMULTAN_MeshTools/resources/__pycache__/__init__.cpython-38.pyc
SIMULTAN_MeshTools/resources/__pycache__/__init__.cpython-39.pyc
SIMULTAN_MeshTools/resources/gui/__init__.py
SIMULTAN_MeshTools/resources/gui/generatepy_gui.cmd
SIMULTAN_MeshTools/resources/gui/main_window.ui
SIMULTAN_MeshTools/resources/gui/ui_main_window.py
SIMULTAN_MeshTools/resources/gui/__pycache__/__init__.cpython-38.pyc
SIMULTAN_MeshTools/resources/gui/__pycache__/__init__.cpython-39.pyc
SIMULTAN_MeshTools/resources/gui/__pycache__/ui_main_window.cpython-38.pyc
SIMULTAN_MeshTools/resources/gui/__pycache__/ui_main_window.cpython-39.pyc
SIMULTAN_MeshTools-1.0.dist-info/LICENSE.txt
SIMULTAN_MeshTools-1.0.dist-info/METADATA
SIMULTAN_MeshTools-1.0.dist-info/WHEEL
SIMULTAN_MeshTools-1.0.dist-info/entry_points.txt
SIMULTAN_MeshTools-1.0.dist-info/top_level.txt
SIMULTAN_MeshTools-1.0.dist-info/RECORD
