Metadata-Version: 2.1
Name: SIMULTAN-MeshTools
Version: 1.0
Summary: Create meshes and map values on meshes for SIMULTAN geometry
Home-page: UNKNOWN
Author: Max Buehler
License: MIT
Keywords: python
Platform: UNKNOWN
Classifier: Development Status :: 4 - Beta
Classifier: Intended Audience :: Developers
Classifier: License :: OSI Approved :: MIT License
Classifier: Programming Language :: Python
Classifier: Programming Language :: Python :: 3
Classifier: Programming Language :: Python :: 3 :: Only
Classifier: Programming Language :: Python :: 3.8
Classifier: Programming Language :: Python :: 3.9
Requires-Python: >=3.8
License-File: LICENSE.txt
Requires-Dist: numpy
Requires-Dist: pygmsh
Requires-Dist: PySimultan (>=0.1.47)
Requires-Dist: trimesh
Requires-Dist: meshio
Requires-Dist: pandas
Requires-Dist: PySide6
Requires-Dist: vg
